{
  "Skills": [
    "React",
    "Redux",
    "NextJs",
    "Gatsby",
    "JavaScript",
    "NodeJs",
    "REST",
    "GraphQL",
    "jQuery",
    "AngularJs",
    "Styled Components",
    "EmotionJs",
    "CSS3",
    "HTML5",
    "Responsive Web Design",
    "PWA",
    "AMP",
    "Web Accessibility",
    "SEO",
    "Webpack/Gulp/Grunt",
    "Photoshop",
    "Architect Agile/Scrum Projects",
    "Team Management"
  ],
  "Professional Experiences": [
    "Manager Experience Technology in Publicis Sapient, Bangalore - From Jan 2017 to till date",
    "Senior Interactive Developer in Publicis Sapient, Bangalore - From Oct 2010 to Dec 2017",
    "Web Developer in Sulekha Media Ltd., Chennai - From Oct 2007 to Sep 2010",
    "Web Master in Crewind Technolgies, Chennai - From Oct 2005 to Sep 2007"
  ],
  "Other Past Experiences": [
    "Tele Calling Executive in Infotech, Chennai - From Mar 2005 to Sep 2005",
    "Administrative Assistant in Sriram Educational Institue, Chennai - From Aug 2003 to Feb 2005"
  ],
  "Education": [
    "General Management for IT Executives (GMITE) from IIM Bangalore - 2012",
    "Master in Computer Applications from University of Madras, Chenni - 2010",
    "Bachelor in Mathematics from University of Madras, Chennai - 2003"
  ],
  "Professional Trainings & Certifications": [
    "MERN Stack - Udemy, Jan 2019",
    "Full Stack JavaScript Architect Program - Publicis Sapient, Jan 2018",
    "Server Side Rendering with React and Redux - Udemy, Dec 2018",
    "Mastering Test Driven Development with React - Udemy, Aug 2018",
    "Advanced JavaScript - Udemy, Dec 2017",
    "React JS Training – Publicis Sapient, Jan 2016"
  ],
  "Contact Details": [
    "Mobile: 91-9900024157",
    "Email: jagadeeswaranster@gmail.com",
    "Skype: jags basappa"
  ]
}
